[{"bestScore":0,"libraryStatus":[false,false,false,false,false,false,false,false,false,true],"playTotalTime":5,"userName":"ddzsf"},{"bestScore":200,"libraryStatus":[false,true,false,true,false,true,true,true,false,false],"playTotalTime":40000,"userName":"sugawara"},{"bestScore":0,"libraryStatus":[false,false,false,false,false,false,false,false,false,false],"playTotalTime":9,"userName":"sdf"},{"bestScore":2555,"libraryStatus":[false,true,false,false,true,false,true,false,false,false],"playTotalTime":0,"userName":"takanashi"}]
